hellohellohello/__init__.py
hellohellohello/hellohellohello.py
hellohellohello-0.0.4.dist-info/METADATA
hellohellohello-0.0.4.dist-info/WHEEL
hellohellohello-0.0.4.dist-info/entry_points.txt
hellohellohello-0.0.4.dist-info/RECORD
