Metadata-Version: 2.4
Name: hellohellohello
Version: 0.0.4
Summary: A simple Python CLI app inspired by the Beatles' 'Hello, Goodbye'. Responds to user input with lyric-inspired opposites.
Author-email: Your Name <your.email@example.com>
Requires-Python: >=3.7
